cloudevents/__init__.py
cloudevents/constants.py
cloudevents/construct.py
cloudevents/model.py
cloudevents/parse.py
cloudevents/serialize.py
cloudevents/webhook.py
cloudevents_python-0.2.1.dist-info/DESCRIPTION.rst
cloudevents_python-0.2.1.dist-info/METADATA
cloudevents_python-0.2.1.dist-info/RECORD
cloudevents_python-0.2.1.dist-info/WHEEL
cloudevents_python-0.2.1.dist-info/metadata.json
cloudevents_python-0.2.1.dist-info/top_level.txt
